smdb_web_server/__init__.py
smdb_web_server-0.4.3.dist-info/licenses/LICENSE
smdb_web_server-0.4.3.dist-info/METADATA
smdb_web_server-0.4.3.dist-info/WHEEL
smdb_web_server-0.4.3.dist-info/top_level.txt
smdb_web_server-0.4.3.dist-info/RECORD
