Metadata-Version: 2.4
Name: smdb_web_server
Version: 0.4.3
Summary: A really basic, not so safe web server.
Home-page: https://github.com/NightKey/smdb-server
Author: Janthó Dávid
Author-email: davidjantho@gmail.com
Project-URL: Bug Tracker, https://github.com/NightKey/smdb-server/issues
Classifier: Development Status :: 4 - Beta
Classifier: Programming Language :: Python :: 3
Classifier: License :: Freeware
Classifier: Operating System :: OS Independent
Requires-Python: >=3.7
License-File: LICENSE
Dynamic: license-file
